[
	{
		"team": {
			"api_football_id": 319,
			"name": "Brann",
			"code": "BRA",
			"country": "Norway",
			"founded": 1908,
			"wiki": "https://en.wikipedia.org/wiki/SK_Brann"
		},
		"venue": {
			"api_football_id": 1176,
			"name": "Brann Stadion",
			"address": "Kniksens plass 1",
			"city": "Bergen",
			"capacity": 17686,
			"surface": "grass",
			"lat": 60.366944,
			"lng": 5.3575,
			"x": 103,
			"y": 852,
			"wiki": "https://en.wikipedia.org/wiki/Brann_Stadion"
		},
		"league": {},
		"images": [
			{
				"name": "1176_001.jpg",
				"source": "https://i.f1g.fr/media/cms/orig/2021/08/17/e49bea2de6e55858525644763cbb1f75bd1be6a865402f50c3fa7bb03f6c4529.jpg",
				"owner": "",
				"width": 0,
				"height": 0,
				"size": 0
			},
			{
				"name": "1176_002.jpg",
				"source": "https://gfx.nrk.no/k8YmKyMCo_ryQZ6AYX2VmQjr2k-77I2UZCARbQDSt7JA.jpg",
				"owner": "",
				"width": 0,
				"height": 0,
				"size": 0
			},
			{
				"name": "1176_003.jpg",
				"source": "https://photos.watchmedier.dk/watchmedier/resize:fill:3840:0:0/plain/https://photos.watchmedier.dk/Images/15354679/ce9eex/ALTERNATES/schema-16_9/brann%2520stadion",
				"owner": "",
				"width": 0,
				"height": 0,
				"size": 0
			},
			{
				"name": "1176_004.jpg",
				"source": "https://g.acdn.no/obscura/API/dynamic/r1/ece5/tr_2000_2000_s_f/0000/berg/2022/4/7/13/IMG-7289.jpg?chk=0FB3C3",
				"owner": "",
				"width": 0,
				"height": 0,
				"size": 0
			},
			{
				"name": "1176_005.jpg",
				"source": "https://www.brann.no/om-stadion/fakta-om-stadion/_/image/5a9fc4ae-1c9a-4c79-bd15-7314b3c9306c:6ce109d75b8c7a65e82bbe8bd612aa6906deb7f9/width-1100/SPV.jpg",
				"owner": "",
				"width": 0,
				"height": 0,
				"size": 0
			},
			{
				"name": "1176_006.jpg",
				"source": "https://upload.wikimedia.org/wikipedia/commons/5/59/Brann_stadium.jpg",
				"owner": "",
				"width": 0,
				"height": 0,
				"size": 0
			}
		],
		"no": 1
	},
	{
		"team": {
			"api_football_id": 320,
			"name": "Kristiansund BK",
			"code": "KRI",
			"country": "Norway",
			"founded": 2003,
			"wiki": "https://en.wikipedia.org/wiki/Kristiansund_BK"
		},
		"venue": {
			"api_football_id": 19680,
			"name": "Nordmøre stadion",
			"address": "Magnar Isaksens vei 1",
			"city": "Kristiansund",
			"capacity": 4444,
			"surface": "artificial turf",
			"lat": 63.124722,
			"lng": 7.718056,
			"x": 178,
			"y": 667,
			"wiki": "https://en.wikipedia.org/wiki/Kristiansund_Stadion"
		},
		"league": {},
		"images": [
			{
				"name": "19680_001.jpg",
				"source": "https://www.kristiansundbk.no/om-stadion/kristiansund-stadion/_/image/bbf0270f-61ab-4228-b00f-d1a0ee912de7:d05317ba25b2eecd445c5a6e0c232d46ef37f2e6/wide-1600-900/Nettsak%20BILDEStadion_drone1.jpg",
				"owner": "",
				"width": 0,
				"height": 0,
				"size": 0
			},
			{
				"name": "19680_002.jpg",
				"source": "https://www.kristiansundbk.no/om-stadion/stadionomradet/_/image/f2f0dcb0-7fe7-4667-bcf7-3ba8176985d5:dfdb3d0f5cd54e189f95094ea6d7c88cf8c3f144/wide-1600-900/image00011.jpeg.jpg",
				"owner": "",
				"width": 0,
				"height": 0,
				"size": 0
			},
			{
				"name": "19680_003.jpg",
				"source": "https://www.kristiansundbk.no/nyheter/pressemelding-fra-kristiansund-ballklubb/_/image/d450f674-b718-4e0d-807b-cdcaf6f15552:423052129859c225d0f906b41f1347bb379a1971/wide-1600-900/stadion1.jpg",
				"owner": "",
				"width": 0,
				"height": 0,
				"size": 0
			},
			{
				"name": "19680_004.jpg",
				"source": "https://www.kristiansundbk.no/nyheter/status-for-arbeidet-pa-nordmore-stadion/_/image/8f942c70-543c-47bc-b5cc-9851a5d84bb0:2a098bab8287bf8e3f6ebefd0a0236b40f3361a5/wide-1600-900/stadi.jpg",
				"owner": "",
				"width": 0,
				"height": 0,
				"size": 0
			},
			{
				"name": "19680_005.jpg",
				"source": "https://www.kristiansundbk.no/nyheter/skifter-kunstgress-pa-nordmore-stadion/_/image/a817d8a7-af7b-4cd9-b6c7-7ea6429e8666:4c7447ad830b37973fb8c347ab5d1e20e596e0f2/wide-1600-900/stadion1.jpg",
				"owner": "",
				"width": 0,
				"height": 0,
				"size": 0
			}
		],
		"no": 2
	},
	{
		"team": {
			"api_football_id": 324,
			"name": "Stromsgodset",
			"code": "STR",
			"country": "Norway",
			"founded": 1907,
			"wiki": "https://en.wikipedia.org/wiki/Str%C3%B8msgodset_Toppfotball"
		},
		"venue": {
			"api_football_id": 1199,
			"name": "Marienlyst Stadion",
			"address": "Schwartzgata 2",
			"city": "Drammen",
			"capacity": 8935,
			"surface": "artificial turf",
			"lat": 59.734444,
			"lng": 10.201389,
			"x": 257,
			"y": 892,
			"wiki": "https://en.wikipedia.org/wiki/Marienlyst_Stadion"
		},
		"league": {},
		"images": [
			{
				"name": "1199_001.jpg",
				"source": "https://g.acdn.no/obscura/API/dynamic/r1/ece5/tr_2000_2000_s_f/0000/dram/2024/11/15/12/Marienlyst%2Bstadion%2B%25282%2Bav%2B5%2529.jpg?chk=C4BE59",
				"owner": "",
				"width": 0,
				"height": 0,
				"size": 0
			},
			{
				"name": "1199_002.jpg",
				"source": "https://stadiumdb.com/pictures/stadiums/nor/marienlyst_stadion/marienlyst_stadion13.jpg",
				"owner": "",
				"width": 0,
				"height": 0,
				"size": 0
			},
			{
				"name": "1199_003.jpg",
				"source": "https://g.acdn.no/obscura/API/dynamic/r1/ece5/tr_2000_2000_s_f/0000/dram/2024/11/15/13/Marienlyst%2Bstadion%2B%25285%2Bav%2B5%2529.jpg?chk=2124D2",
				"owner": "",
				"width": 0,
				"height": 0,
				"size": 0
			},
			{
				"name": "1199_004.jpg",
				"source": "https://assets.simpleviewcms.com/simpleview/image/fetch/c_fill,h_1080,w_1920/f_jpg/q_65/https://media.newmindmedia.com/TellUs/image/%3Ffile%3DMarienlystStadion_1607425384.png&dh%3D450&dw%3D800&t%3D4",
				"owner": "",
				"width": 0,
				"height": 0,
				"size": 0
			}
		],
		"no": 3
	},
	{
		"team": {
			"api_football_id": 325,
			"name": "Tromso",
			"code": "TRO",
			"country": "Norway",
			"founded": 1920,
			"wiki": "https://en.wikipedia.org/wiki/Troms%C3%B8_IL"
		},
		"venue": {
			"api_football_id": 19681,
			"name": "Romssa Arena",
			"address": "Stadionveien 3",
			"city": "Tromsø",
			"capacity": 8585,
			"surface": "artificial turf",
			"lat": 69.648954,
			"lng": 18.934582,
			"x": 535,
			"y": 146,
			"wiki": "https://en.wikipedia.org/wiki/Romssa_Arena"
		},
		"league": {},
		"images": [
			{
				"name": "19681_001.jpg",
				"source": "https://gfx.nrk.no/MTwcI7nVUllhEL8H-0oXfwDcBkuStCx-lkdBJsmInQ8Q.jpg",
				"owner": "",
				"width": 0,
				"height": 0,
				"size": 0
			},
			{
				"name": "19681_002.jpg",
				"source": "https://pbs.twimg.com/media/FsXbz6yXsAALQ7t.jpg",
				"owner": "",
				"width": 0,
				"height": 0,
				"size": 0
			},
			{
				"name": "19681_003.jpg",
				"source": "https://upload.wikimedia.org/wikipedia/commons/thumb/4/42/West_Stand.JPG/1200px-West_Stand.JPG",
				"owner": "",
				"width": 0,
				"height": 0,
				"size": 0
			},
			{
				"name": "19681_004.jpg",
				"source": "https://pbs.twimg.com/media/GNDEAItXoAA6vLD?format=jpg&name=4096x4096",
				"owner": "",
				"width": 0,
				"height": 0,
				"size": 0
			}
		],
		"no": 4
	},
	{
		"team": {
			"api_football_id": 326,
			"name": "Valerenga",
			"code": "VAL",
			"country": "Norway",
			"founded": 1913,
			"wiki": "https://en.wikipedia.org/wiki/V%C3%A5lerenga_Fotball"
		},
		"venue": {
			"api_football_id": 1203,
			"name": "Intility Arena",
			"address": "Innspurten 1",
			"city": "Oslo",
			"capacity": 18000,
			"surface": "artificial turf",
			"lat": 59.917778,
			"lng": 10.806944,
			"x": 276,
			"y": 881,
			"wiki": "https://en.wikipedia.org/wiki/Intility_Arena"
		},
		"league": {},
		"images": [
			{
				"name": "1203_001.jpg",
				"source": "https://upload.wikimedia.org/wikipedia/commons/4/49/Intility_Arena_%28bilde05%29_%288._september_2018%29.jpg",
				"owner": "",
				"width": 0,
				"height": 0,
				"size": 0
			},
			{
				"name": "1203_002.jpg",
				"source": "https://www.hent.no/wp-content/uploads/2021/06/1192_07.jpg",
				"owner": "",
				"width": 0,
				"height": 0,
				"size": 0
			},
			{
				"name": "1203_003.jpg",
				"source": "https://www.rakennuslehti.fi/wp-content/uploads/2018/04/unisport_valerenga-e1524148042588-2048x1195.jpg",
				"owner": "",
				"width": 0,
				"height": 0,
				"size": 0
			},
			{
				"name": "1203_004.jpg",
				"source": "https://www.vif-fotball.no/english-information/valerenga%20Kultur-%20og%20idrettspark/_/image/bc0ddcf8-4487-4a3b-822c-52f243b2cb8a:9f142d072897bffb6a569cc8a2e7c552992fa13d/wide-1600-900/TIFO%20(1).jpg",
				"owner": "",
				"width": 0,
				"height": 0,
				"size": 0
			},
			{
				"name": "1203_005.jpg",
				"source": "https://www.vif-fotball.no/english-information/media-information/_/image/285b3627-1675-4f31-9bf2-545fad643845:80a7717123e381ec9c93a50101579173e3c962ae/wide-1600-900/IMG_1259.jpg",
				"owner": "",
				"width": 0,
				"height": 0,
				"size": 0
			}
		],
		"no": 5
	},
	{
		"team": {
			"api_football_id": 327,
			"name": "Bodo/Glimt",
			"code": "BOD",
			"country": "Norway",
			"founded": 1916,
			"wiki": "https://en.wikipedia.org/wiki/FK_Bod%C3%B8/Glimt"
		},
		"venue": {
			"api_football_id": 1175,
			"name": "Aspmyra Stadion",
			"address": "Håloglandsgata 30",
			"city": "Bodø",
			"capacity": 8270,
			"surface": "artificial turf",
			"lat": 67.276667,
			"lng": 14.384444,
			"x": 390,
			"y": 351,
			"wiki": "https://en.wikipedia.org/wiki/Aspmyra_Stadion"
		},
		"league": {},
		"images": [
			{
				"name": "1175_001.jpg",
				"source": "https://pbs.twimg.com/media/Ec5LfjUWsAYkwuK.jpg:large",
				"owner": "",
				"width": 0,
				"height": 0,
				"size": 0
			},
			{
				"name": "1175_002.jpg",
				"source": "https://gfx.nrk.no/aybdjIrWW6h7GYuUMZUAJw1fohU3sET_rIjViK6B1rIA.jpg",
				"owner": "",
				"width": 0,
				"height": 0,
				"size": 0
			},
			{
				"name": "1175_003.jpg",
				"source": "https://pbs.twimg.com/media/Fe9LoMlXEAA4wgg.jpg:large",
				"owner": "",
				"width": 0,
				"height": 0,
				"size": 0
			},
			{
				"name": "1175_004.jpg",
				"source": "https://pbs.twimg.com/media/FgkupIlX0AE4USh.jpg:large",
				"owner": "",
				"width": 0,
				"height": 0,
				"size": 0
			}
		],
		"no": 6
	},
	{
		"team": {
			"api_football_id": 328,
			"name": "Haugesund",
			"code": "HAU",
			"country": "Norway",
			"founded": 1993,
			"wiki": "https://en.wikipedia.org/wiki/FK_Haugesund"
		},
		"venue": {
			"api_football_id": 12130,
			"name": "Haugesund Sparebank Arena",
			"address": "Karmsundggaten 169",
			"city": "Haugesund",
			"capacity": 8950,
			"surface": "grass",
			"lat": 59.413,
			"lng": 5.279,
			"x": 100,
			"y": 912,
			"wiki": "https://en.wikipedia.org/wiki/Haugesund_Stadion"
		},
		"league": {},
		"images": [
			{
				"name": "12130_001.jpg",
				"source": "https://sortitoutsi.b-cdn.net/uploads/media_2024/tGJAQLRDY8x5XMKzTbccDT1YSmv1HexHBTBOOnf9.jpg",
				"owner": "",
				"width": 0,
				"height": 0,
				"size": 0
			},
			{
				"name": "12130_002.jpg",
				"source": "https://pbs.twimg.com/media/FeCvhigXwAMUxL1.jpg:large",
				"owner": "",
				"width": 0,
				"height": 0,
				"size": 0
			},
			{
				"name": "12130_003.jpg",
				"source": "https://www.aafk.no/nyheter/bortebilletter-haugesund/_/image/d9f37ae9-7924-4a86-b8f4-0d8c6a6a6b22:02852d419dd1d45dcb48283629242bd785bc373a/wide-1600-900/NTB_rTM8i7gIvIs.jpg",
				"owner": "",
				"width": 0,
				"height": 0,
				"size": 0
			},
			{
				"name": "12130_004.jpg",
				"source": "https://pbs.twimg.com/media/Fu8Zn3yWcAADjAg.jpg:large",
				"owner": "",
				"width": 0,
				"height": 0,
				"size": 0
			},
			{
				"name": "12130_005.jpg",
				"source": "https://akrehamn-vekst.no/wp-content/uploads/2021/08/Haugesund-Sparebank-Arena.jpg",
				"owner": "",
				"width": 0,
				"height": 0,
				"size": 0
			}
		],
		"no": 7
	},
	{
		"team": {
			"api_football_id": 329,
			"name": "Molde",
			"code": "MOL",
			"country": "Norway",
			"founded": 1911,
			"wiki": "https://en.wikipedia.org/wiki/Molde_FK"
		},
		"venue": {
			"api_football_id": 1184,
			"name": "Aker Stadion",
			"address": "Julsundveien 14, Reknes",
			"city": "Molde",
			"capacity": 11800,
			"surface": "artificial turf",
			"lat": 62.733333,
			"lng": 7.147778,
			"x": 160,
			"y": 694,
			"wiki": "https://en.wikipedia.org/wiki/Aker_Stadion"
		},
		"league": {},
		"images": [
			{
				"name": "1184_001.jpg",
				"source": "https://telegrafi.com/wp-content/uploads/2018/02/Aker-Stadion.jpg",
				"owner": "",
				"width": 0,
				"height": 0,
				"size": 0
			},
			{
				"name": "1184_002.jpg",
				"source": "https://www.footballticketnet.fr/theme/images/venues_cover/Buy-Aker_Stadion-Football-Tickets-FootballTicketNet-Cover.1726135284.png",
				"owner": "",
				"width": 0,
				"height": 0,
				"size": 0
			},
			{
				"name": "1184_003.jpg",
				"source": "https://pbs.twimg.com/media/Dl2XrmSXoAE3tl-.jpg",
				"owner": "",
				"width": 0,
				"height": 0,
				"size": 0
			},
			{
				"name": "1184_004.jpg",
				"source": "https://www.info-stades.fr/uploads/stades/molde-aker-stadion-aerial-20582.jpg",
				"owner": "",
				"width": 0,
				"height": 0,
				"size": 0
			}
		],
		"no": 8
	},
	{
		"team": {
			"api_football_id": 331,
			"name": "Rosenborg",
			"code": "ROS",
			"country": "Norway",
			"founded": 1917,
			"wiki": "https://en.wikipedia.org/wiki/Rosenborg_BK"
		},
		"venue": {
			"api_football_id": 1190,
			"name": "Lerkendal Stadion",
			"address": "Klæbuveien 125",
			"city": "Trondheim",
			"capacity": 21850,
			"surface": "grass",
			"lat": 63.4123,
			"lng": 10.4045,
			"x": 263,
			"y": 646,
			"wiki": "https://en.wikipedia.org/wiki/Lerkendal_Stadion"
		},
		"league": {},
		"images": [
			{
				"name": "1190_001.jpg",
				"source": "https://pbs.twimg.com/media/GSiZ2KUWUAANDiY?format=jpg&name=large",
				"owner": "",
				"width": 0,
				"height": 0,
				"size": 0
			},
			{
				"name": "1190_002.jpg",
				"source": "https://pbs.twimg.com/media/GUJstBlXAAAo467.jpg:large",
				"owner": "",
				"width": 0,
				"height": 0,
				"size": 0
			},
			{
				"name": "1190_003.jpg",
				"source": "https://cdn.shopify.com/s/files/1/0705/7352/3240/articles/Lerkandal_1000_1000.jpg?v=1691500269",
				"owner": "",
				"width": 0,
				"height": 0,
				"size": 0
			},
			{
				"name": "1190_004.jpg",
				"source": "https://pbs.twimg.com/media/DkuGfT7WsAAWZuJ.jpg:large",
				"owner": "",
				"width": 0,
				"height": 0,
				"size": 0
			},
			{
				"name": "1190_005.jpg",
				"source": "https://pbs.twimg.com/media/DkuGfT7WsAAWZuJ.jpg:large",
				"owner": "",
				"width": 0,
				"height": 0,
				"size": 0
			}
		],
		"no": 9
	},
	{
		"team": {
			"api_football_id": 332,
			"name": "Sandefjord",
			"code": "SAN",
			"country": "Norway",
			"founded": 1998,
			"wiki": "https://en.wikipedia.org/wiki/Sandefjord_Fotball"
		},
		"venue": {
			"api_football_id": 20418,
			"name": "Jotun Arena",
			"address": "Nygårdsveien 84",
			"city": "Sandefjord",
			"capacity": 6598,
			"surface": "grass",
			"lat": 59.13725,
			"lng": 10.17969,
			"x": 256,
			"y": 929,
			"wiki": "https://en.wikipedia.org/wiki/Sandefjord_Arena"
		},
		"league": {},
		"images": [
			{
				"name": "20418_001.jpg",
				"source": "https://pbs.twimg.com/media/F_EYghQWEAEl-ij.jpg:large",
				"owner": "",
				"width": 0,
				"height": 0,
				"size": 0
			},
			{
				"name": "20418_002.jpg",
				"source": "https://www.sandefjordfotball.no/om-stadion/veibeskrivelse-til-komplett-arena/_/image/05a39e9b-e64e-40d2-9d1d-bc8d9b5c8ffd:bb8a520abc1624557983013b9456c7a218b1c5c4/wide-1600-900/IMG_6457.JPG.jpg",
				"owner": "",
				"width": 0,
				"height": 0,
				"size": 0
			},
			{
				"name": "20418_003.jpg",
				"source": "https://kenneth-jansen.com/release%20arena.jpg",
				"owner": "",
				"width": 0,
				"height": 0,
				"size": 0
			},
			{
				"name": "20418_004.jpg",
				"source": "https://pbs.twimg.com/media/GOB4w05X0AEbLZK.jpg:large",
				"owner": "",
				"width": 0,
				"height": 0,
				"size": 0
			}
		],
		"no": 10
	},
	{
		"team": {
			"api_football_id": 333,
			"name": "Sarpsborg 08 FF",
			"code": "SAR",
			"country": "Norway",
			"founded": 1928,
			"wiki": "https://en.wikipedia.org/wiki/Sarpsborg_08_FF"
		},
		"venue": {
			"api_football_id": 1193,
			"name": "Sarpsborg Stadion",
			"address": "Haftor Jonssons gate 19",
			"city": "Sarpsborg",
			"capacity": 8022,
			"surface": "artificial turf",
			"lat": 59.286111,
			"lng": 11.0975,
			"x": 285,
			"y": 920,
			"wiki": "https://en.wikipedia.org/wiki/Sarpsborg_Stadion"
		},
		"league": {},
		"images": [
			{
				"name": "1193_001.jpg",
				"source": "https://g.acdn.no/obscura/API/dynamic/r1/ece5/tr_2000_2000_s_f/0000/sarp/2023/4/27/15/DJI_0009.jpeg?chk=DAC7CC",
				"owner": "",
				"width": 0,
				"height": 0,
				"size": 0
			},
			{
				"name": "1193_002.jpg",
				"source": "https://g.acdn.no/obscura/API/dynamic/r1/ece5/tr_2000_2000_s_f/0000/sarp/2020/4/1/16/Sstadion.jpg?chk=C98B75",
				"owner": "",
				"width": 0,
				"height": 0,
				"size": 0
			},
			{
				"name": "1193_003.jpg",
				"source": "https://cdn.blogg.no/content/uploads/sites/461/2024/11/12192546/20241105_190335-scaled.jpg",
				"owner": "",
				"width": 0,
				"height": 0,
				"size": 0
			}
		],
		"no": 11
	},
	{
		"team": {
			"api_football_id": 759,
			"name": "Viking",
			"code": "VIK",
			"country": "Norway",
			"founded": 1899,
			"wiki": "https://en.wikipedia.org/wiki/Viking_FK"
		},
		"venue": {
			"api_football_id": 1204,
			"name": "SR-Bank Arena",
			"address": "Gamle Jåttåvågen 3, Jåttåvågen",
			"city": "Stavanger",
			"capacity": 16508,
			"surface": "artificial turf",
			"lat": 58.914722,
			"lng": 5.730556,
			"x": 115,
			"y": 943,
			"wiki": "https://en.wikipedia.org/wiki/Viking_Stadion"
		},
		"league": {},
		"images": [
			{
				"name": "1204_001.jpg",
				"source": "https://www.polytan.fr/wp-content/uploads/2020/04/Titelbild.jpg",
				"owner": "",
				"width": 0,
				"height": 0,
				"size": 0
			},
			{
				"name": "1204_002.jpg",
				"source": "https://www.polytan.fr/wp-content/uploads/2020/03/SRbankArena12_1900x800.jpg",
				"owner": "",
				"width": 0,
				"height": 0,
				"size": 0
			},
			{
				"name": "1204_003.jpg",
				"source": "https://www.polytan.fr/wp-content/uploads/2020/03/SRbankArena21_1900x800.jpg",
				"owner": "",
				"width": 0,
				"height": 0,
				"size": 0
			},
			{
				"name": "1204_004.jpg",
				"source": "https://www.vikingfotball.no/nyheter/nm-finale-pa-sr-bank-arena/_/image/832e061a-6697-46f1-8a4b-ece9c2c990cc:7b287e9e8750a92f969513ff4afb920c9481844b/wide-1600-900/StadionNTB2021-2.jpg",
				"owner": "",
				"width": 0,
				"height": 0,
				"size": 0
			}
		],
		"no": 12
	},
	{
		"team": {
			"api_football_id": 2142,
			"name": "Bryne",
			"code": "BRY",
			"country": "Norway",
			"founded": 1926,
			"wiki": "https://en.wikipedia.org/wiki/Bryne_FK"
		},
		"venue": {
			"api_football_id": 2793,
			"name": "Bryne Stadion",
			"address": "Trallfavegen 3",
			"city": "Bryne",
			"capacity": 10133,
			"surface": "grass",
			"lat": 58.729767,
			"lng": 5.649772,
			"x": 112,
			"y": 955,
			"wiki": "https://en.wikipedia.org/wiki/Bryne_Stadion"
		},
		"league": {},
		"images": [
			{
				"name": "2793_001.jpg",
				"source": "https://paabortebane.no/wp-content/uploads/2020/09/Bryne-red-scaled.jpg",
				"owner": "",
				"width": 0,
				"height": 0,
				"size": 0
			},
			{
				"name": "2793_002.jpg",
				"source": "https://www.brynefk.no/om-stadion/Bryne%20Stadion/_/image/96fb33b6-a748-48de-98f9-c714a26d8189:f559c73dbaab8aef066ae2e3a520d760b11b9d49/wide-1170-810/IMG_3415.jpeg",
				"owner": "",
				"width": 0,
				"height": 0,
				"size": 0
			},
			{
				"name": "2793_003.jpg",
				"source": "https://www.brynefk.no/om-stadion/Bryne%20Stadion/_/image/aef69122-97eb-4fee-b60b-f7c63cc6451d:f32d8325d02860ba64404f73b7ece569a6394006/wide-1600-900/IMG_3414.jpeg.jpg",
				"owner": "",
				"width": 0,
				"height": 0,
				"size": 0
			}
		],
		"no": 13
	},
	{
		"team": {
			"api_football_id": 2143,
			"name": "KFUM Oslo",
			"code": "KFU",
			"country": "Norway",
			"founded": 1939,
			"wiki": "https://en.wikipedia.org/wiki/KFUM-Kameratene_Oslo"
		},
		"venue": {
			"api_football_id": 1179,
			"name": "KFUM Arena",
			"address": "Ekebergveien 101",
			"city": "Oslo",
			"capacity": 3300,
			"surface": "artificial turf",
			"lat": 59.89,
			"lng": 10.780833,
			"x": 275,
			"y": 882,
			"wiki": "https://en.wikipedia.org/wiki/KFUM_Arena"
		},
		"league": {},
		"images": [
			{
				"name": "1179_001.jpg",
				"source": "https://www.kaaffa.no/om-stadion/kfum-arena/_/image/eab76ad3-9354-458a-bf66-bdaaa2902612:e063dbcf1219ff2e235eb4f10f61658e7b7f3670/wide-1170-810/DJI_0108x.jpg",
				"owner": "",
				"width": 0,
				"height": 0,
				"size": 0
			},
			{
				"name": "1179_002.jpg",
				"source": "https://www.kaaffa.no/om-stadion/_/image/aaceef82-5868-466b-b814-ce91b6bd50ca:61df65b83e46167ef0f8419e1c41dc481a628f59/wide-1600-900/DJI_0114xx.jpg",
				"owner": "",
				"width": 0,
				"height": 0,
				"size": 0
			},
			{
				"name": "1179_003.jpg",
				"source": "https://www.kaaffa.no/om-stadion/kfum-arena/_/image/2f557e47-c447-4aad-9e2a-7978ddf5e3e8:0f4aad8d9c591b832ff63ea368c1bdc7ebc2c4b1/wide-1170-810/DJI_0126.JPG",
				"owner": "",
				"width": 0,
				"height": 0,
				"size": 0
			}
		],
		"no": 14
	},
	{
		"team": {
			"api_football_id": 2149,
			"name": "Fredrikstad",
			"code": "FRE",
			"country": "Norway",
			"founded": 1903,
			"wiki": "https://en.wikipedia.org/wiki/Fredrikstad_FK"
		},
		"venue": {
			"api_football_id": 2792,
			"name": "Nye Fredrikstad Stadion",
			"address": "K. G. Meldahls vei 9, Kråkerøy",
			"city": "Fredrikstad",
			"capacity": 12565,
			"surface": "artificial turf",
			"lat": 59.213,
			"lng": 10.927,
			"x": 280,
			"y": 925,
			"wiki": "https://en.wikipedia.org/wiki/Fredrikstad_Stadion"
		},
		"league": {},
		"images": [
			{
				"name": "2792_001.jpg",
				"source": "https://g.acdn.no/obscura/API/dynamic/r1/ece5/tr_2000_2000_s_f/0000/fred/2017/11/14/15/1510671350596.jpg?chk=E57B78",
				"owner": "",
				"width": 0,
				"height": 0,
				"size": 0
			},
			{
				"name": "2792_002.jpg",
				"source": "https://www.fredrikstadfk.no/nyheter/lanserer-ny-kommersiell-satsning--apner-konseptbutikk/_/image/5e75e55a-a81b-48f9-9855-2cce6ac32f13:6c5562351db33ce621d0d5065d974bbc31210678/width-1100/0UE8Ojexen8.jpg",
				"owner": "",
				"width": 0,
				"height": 0,
				"size": 0
			},
			{
				"name": "2792_003.jpg",
				"source": "https://blogger.googleusercontent.com/img/b/R29vZ2xl/AVvXsEgRaomdRc7iwYfa8bMjfzZ_ggCYG7UXSdSezTJ_dJqTvNVUz6XPbQn27jBp7doi0t_zJAQ-KElT70yp9SrJcYNLUHmP-q3WTaZrJboLofS3XChZBmxzj85uItsT5wM4a7JYBjjdXvCl20VQ/s1600/Fredrikstad+34.JPG",
				"owner": "",
				"width": 0,
				"height": 0,
				"size": 0
			},
			{
				"name": "2792_004.jpg",
				"source": "https://pbs.twimg.com/media/GJb4hbzW8AARM_H?format=jpg&name=4096x4096",
				"owner": "",
				"width": 0,
				"height": 0,
				"size": 0
			}
		],
		"no": 15
	},
	{
		"team": {
			"api_football_id": 2159,
			"name": "Ham-Kam",
			"code": "HAM",
			"country": "Norway",
			"founded": 1918,
			"wiki": "https://en.wikipedia.org/wiki/Hamarkameratene"
		},
		"venue": {
			"api_football_id": 1177,
			"name": "Briskeby Arena",
			"address": "Arenavegen 2, Briskebyen",
			"city": "Hamar",
			"capacity": 8068,
			"surface": "artificial turf",
			"lat": 60.795556,
			"lng": 11.092222,
			"x": 285,
			"y": 824,
			"wiki": "https://en.wikipedia.org/wiki/Briskeby_Stadion"
		},
		"league": {},
		"images": [
			{
				"name": "1177_001.jpg",
				"source": "https://g.acdn.no/obscura/API/dynamic/r1/ece5/tr_2000_2000_s_f/0000/haar/2022/10/21/11/flyfoto-briskeby-17.jpg?chk=4EBEAA",
				"owner": "",
				"width": 0,
				"height": 0,
				"size": 0
			},
			{
				"name": "1177_002.jpg",
				"source": "https://www.hamkam.no/nyheter/landskamper-pa-briskeby/_/image/e115116e-750e-494e-9173-e6e86edec184:afc35351adc8bfff3c388b05525001dd3229214a/wide-1600-900/Briskeby.jpg",
				"owner": "",
				"width": 0,
				"height": 0,
				"size": 0
			},
			{
				"name": "1177_003.jpg",
				"source": "https://g.acdn.no/obscura/API/dynamic/r1/ece5/tr_2000_2000_s_f/0000/haar/2022/10/21/11/briskeby-7.jpg?chk=B2B178",
				"owner": "",
				"width": 0,
				"height": 0,
				"size": 0
			},
			{
				"name": "1177_004.jpg",
				"source": "https://briskebystadion.com/wp-content/uploads/2024/10/briskeby3.jpg",
				"owner": "",
				"width": 0,
				"height": 0,
				"size": 0
			}
		],
		"no": 16
	},
	{
		"team": {
			"api_football_id": 321,
			"name": "Lillestrom",
			"code": "LIL",
			"country": "Norway",
			"founded": 1917,
			"wiki": "https://en.wikipedia.org/wiki/Lillestr%C3%B8m_SK"
		},
		"venue": {
			"api_football_id": 1182,
			"name": "Åråsen Stadion",
			"address": "C.J. Hansensvej 3b",
			"city": "Kjeller",
			"capacity": 11637,
			"surface": "grass",
			"lat": 59.964,
			"lng": 11.063,
			"x": 284,
			"y": 878,
			"wiki": "https://en.wikipedia.org/wiki/%C3%85r%C3%A5sen_Stadion"
		},
		"league": {},
		"images": [
			{
				"name": "1182_001.jpg",
				"source": "https://pbs.twimg.com/media/Fa3EAclXwAAXpee.jpg:large",
				"owner": "",
				"width": 0,
				"height": 0,
				"size": 0
			},
			{
				"name": "1182_002.jpg",
				"source": "https://kenneth-jansen.com/arasen%20stadion.jpg",
				"owner": "",
				"width": 0,
				"height": 0,
				"size": 0
			},
			{
				"name": "1182_003.jpg",
				"source": "https://upload.wikimedia.org/wikipedia/commons/thumb/c/c6/%C3%85r%C3%A5sen_stadion.jpg/1200px-%C3%85r%C3%A5sen_stadion.jpg",
				"owner": "",
				"width": 0,
				"height": 0,
				"size": 0
			},
			{
				"name": "1182_004.jpg",
				"source": "https://stadiumdb.com/pictures/stadiums/nor/arasen_stadion/arasen_stadion11.jpg",
				"owner": "",
				"width": 0,
				"height": 0,
				"size": 0
			},
			{
				"name": "1182_005.jpg",
				"source": "https://groundhopping.carlluis.de/storage/fotos/large/248/Arasen%20stadion-009-Haupttribuene.jpg",
				"owner": "",
				"width": 0,
				"height": 0,
				"size": 0
			}
		],
		"no": 17
	},
	{
		"team": {
			"api_football_id": 322,
			"name": "Ranheim",
			"code": "RAN",
			"country": "Norway",
			"founded": 1901,
			"wiki": "https://en.wikipedia.org/wiki/Ranheim_Fotball"
		},
		"venue": {
			"api_football_id": 1188,
			"name": "EXTRA Arena",
			"address": "Ranheimsveien 166",
			"city": "Ranheim",
			"capacity": 3000,
			"surface": "artificial turf",
			"lat": 63.428376,
			"lng": 10.52401,
			"x": 267,
			"y": 645,
			"wiki": "https://en.wikipedia.org/wiki/EXTRA_Arena"
		},
		"league": {},
		"images": [
			{
				"name": "1188_001.jpg",
				"source": "https://static.wixstatic.com/media/2edd38_031d6cd67d9f45979fd7bf907c91a06a~mv2_d_3264_1840_s_2.jpg/v1/fill/w_1600%2Ch_901%2Cal_c%2Cq_90/file.jpg",
				"owner": "",
				"width": 0,
				"height": 0,
				"size": 0
			},
			{
				"name": "1188_002.jpg",
				"source": "https://paabortebane.no/wp-content/uploads/2019/05/EXTRA-Arena.jpg",
				"owner": "",
				"width": 0,
				"height": 0,
				"size": 0
			},
			{
				"name": "1188_003.jpg",
				"source": "https://www.ranheimfotball.no/nyheter/fast-plass-2017/_/image/7ddf24bb-2505-416b-8134-b02cfa9df0a9:5ee834fe15c4b2a1d2f57f5dadcfeeedbeee2c69/wide-1600-900/DSC_3364.JPG.jpg",
				"owner": "",
				"width": 0,
				"height": 0,
				"size": 0
			}
		],
		"no": 18
	},
	{
		"team": {
			"api_football_id": 323,
			"name": "Stabaek",
			"code": "STA",
			"country": "Norway",
			"founded": 1912,
			"wiki": "https://en.wikipedia.org/wiki/Stab%C3%A6k_Fotball"
		},
		"venue": {
			"api_football_id": 1196,
			"name": "Nadderud Stadion",
			"address": "Gamle Ringeriksvei 59, Nadderud, Stabekk",
			"city": "Bærum",
			"capacity": 7000,
			"surface": "grass",
			"lat": 59.921111,
			"lng": 10.581111,
			"x": 269,
			"y": 880,
			"wiki": "https://en.wikipedia.org/wiki/Nadderud_Stadion"
		},
		"league": {},
		"images": [
			{
				"name": "1196_001.jpg",
				"source": "https://upload.wikimedia.org/wikipedia/commons/thumb/b/b7/Nadderud_stadion_IMG_6283.JPG/2560px-Nadderud_stadion_IMG_6283.JPG",
				"owner": "",
				"width": 0,
				"height": 0,
				"size": 0
			},
			{
				"name": "1196_002.jpg",
				"source": "https://premium.vgc.no/v2/images/f9f12361-138d-45cc-9c89-d454c755e6e1?fit=crop&format=auto&h=1365&w=2048&s=bc61db93b3652281c21a1bd371419ba3b5f186c5",
				"owner": "",
				"width": 0,
				"height": 0,
				"size": 0
			},
			{
				"name": "1196_003.jpg",
				"source": "https://upload.wikimedia.org/wikipedia/commons/f/f5/Nadderud_stadion-main_stand.jpg",
				"owner": "",
				"width": 0,
				"height": 0,
				"size": 0
			},
			{
				"name": "1196_004.jpg",
				"source": "https://www.stabak.no/nadderud-stadion/stadionreglement/_/image/35d45a0f-c4bd-4ecc-af76-fb2eb5e12eed:7a5a4c86ea1effc26c8edb78ecf7e7bad840a234/wide-1600-900/20181117-stb-nadderud-reglement.jpg",
				"owner": "",
				"width": 0,
				"height": 0,
				"size": 0
			},
			{
				"name": "1196_005.jpg",
				"source": "https://i.eurosport.com/2023/05/30/3715502-75599968-2560-1440.jpg",
				"owner": "",
				"width": 0,
				"height": 0,
				"size": 0
			}
		],
		"no": 19
	},
	{
		"team": {
			"api_football_id": 330,
			"name": "ODD Ballklubb",
			"code": "ODD",
			"country": "Norway",
			"founded": 1894,
			"wiki": "https://en.wikipedia.org/wiki/Odds_BK"
		},
		"venue": {
			"api_football_id": 1187,
			"name": "Skagerak Arena",
			"address": "Fridtjof Nansensgatan 21-23, Falkum",
			"city": "Skien",
			"capacity": 13500,
			"surface": "artificial turf",
			"lat": 59.211111,
			"lng": 9.589722,
			"x": 237,
			"y": 925,
			"wiki": "https://en.wikipedia.org/wiki/Skagerak_Arena"
		},
		"league": {},
		"images": [
			{
				"name": "1187_001.jpg",
				"source": "https://upload.wikimedia.org/wikipedia/commons/6/60/Skagerak_Arena_2008.JPG",
				"owner": "",
				"width": 0,
				"height": 0,
				"size": 0
			},
			{
				"name": "1187_002.jpg",
				"source": "https://football-stadiums.ru/wp-content/uploads/2023/11/skagerak-arena-01.jpg",
				"owner": "",
				"width": 0,
				"height": 0,
				"size": 0
			},
			{
				"name": "1187_003.jpg",
				"source": "https://www.odd.no/nyheter/ny-treningskamp-pa-skagerak-arena/_/image/5a4540a7-547b-4ed7-bcb7-a242fc201ba1:62322610c8477ac89807c27f2e99a318b4811313/wide-1600-900/skagerak%20Arena%202021.jpg",
				"owner": "",
				"width": 0,
				"height": 0,
				"size": 0
			},
			{
				"name": "1187_004.jpg",
				"source": "https://g.acdn.no/obscura/API/dynamic/r1/ece5/tr_2000_2000_s_f/0000/teav/2021/5/21/10/08SPO_01-01-DSC_28ght07.jpg?chk=5BF126",
				"owner": "",
				"width": 0,
				"height": 0,
				"size": 0
			},
			{
				"name": "1187_005.jpg",
				"source": "https://g.acdn.no/obscura/API/dynamic/r1/ece5/tr_2000_2000_s_f/0000/teav/2021/5/21/10/08SPO_01-01-DSC_28ght07.jpg?chk=5BF126",
				"owner": "",
				"width": 0,
				"height": 0,
				"size": 0
			}
		],
		"no": 20
	},
	{
		"team": {
			"api_football_id": 334,
			"name": "Start",
			"code": "STA",
			"country": "Norway",
			"founded": 1905,
			"wiki": "https://en.wikipedia.org/wiki/IK_Start"
		},
		"venue": {
			"api_football_id": 1197,
			"name": "Sparebanken Sør Arena",
			"address": "Stadionveien 21",
			"city": "Kristiansand",
			"capacity": 14563,
			"surface": "artificial turf",
			"lat": 58.153611,
			"lng": 8.028611,
			"x": 188,
			"y": 990,
			"wiki": "https://en.wikipedia.org/wiki/S%C3%B8r_Arena"
		},
		"league": {},
		"images": [
			{
				"name": "1197_001.jpg",
				"source": "https://premium.vgc.no/v2/images/e8226ac5-b2ef-435d-b259-573890fcc16d?fit=crop&format=auto&h=1535&w=2048&s=12ab4734f091ad094430335b80a8fdb73b2f50e3",
				"owner": "",
				"width": 0,
				"height": 0,
				"size": 0
			},
			{
				"name": "1197_002.jpg",
				"source": "https://premium.vgc.no/v2/images/70988328-c77d-4aa6-9d44-587046a5c7ca?fit=crop&format=auto&h=988&w=1900&s=1de9ece1046c9a3f6dcc53f159a8e1145a55d6ce",
				"owner": "",
				"width": 0,
				"height": 0,
				"size": 0
			},
			{
				"name": "1197_003.jpg",
				"source": "https://www.ikstart.no/nyheter/kampoversikt-sparebanken-sor-arena-hosten-2024/_/image/6cb7603c-f335-4a36-8094-bc9d5ecef463:93e977a14aa133a756aa1db3b608e7b03081d2c8/wide-1600-900/Sparebanken%20S%C3%B8r%20Arena.jpg",
				"owner": "",
				"width": 0,
				"height": 0,
				"size": 0
			},
			{
				"name": "1197_004.jpg",
				"source": "https://www.lundsentrum.no/media/3cpl33w2/thumbnail_image002.jpg",
				"owner": "",
				"width": 0,
				"height": 0,
				"size": 0
			},
			{
				"name": "1197_005.jpg",
				"source": "https://premium.vgc.no/v2/images/03ace206-655c-447d-9bfe-a3fa04d78024?fit=crop&format=auto&h=1266&w=1900&s=0d9e913f2c2b7dfd74db09944205b12421e08bb8",
				"owner": "",
				"width": 0,
				"height": 0,
				"size": 0
			},
			{
				"name": "1197_006.jpg",
				"source": "https://g.acdn.no/obscura/API/dynamic/r1/ece5/tr_2000_2000_s_f/0000/krsn/2024/11/13/13/NTB_pOOVtYkhaNE.jpg?chk=6E6640",
				"owner": "",
				"width": 0,
				"height": 0,
				"size": 0
			}
		],
		"no": 21
	},
	{
		"team": {
			"api_football_id": 757,
			"name": "Aalesund",
			"code": "AAL",
			"country": "Norway",
			"founded": 1914,
			"wiki": "https://en.wikipedia.org/wiki/Aalesunds_FK"
		},
		"venue": {
			"api_football_id": 1174,
			"name": "Color Line Stadion",
			"address": "Sjømannsveien 14",
			"city": "Ålesund",
			"capacity": 10778,
			"surface": "artificial turf",
			"lat": 62.469722,
			"lng": 6.187194,
			"x": 129,
			"y": 712,
			"wiki": "https://en.wikipedia.org/wiki/Color_Line_Stadion"
		},
		"league": {},
		"images": [
			{
				"name": "1174_001.jpg",
				"source": "https://www.aafk.no/om-klubben/om-stadion/_/image/b910d55a-7389-429b-948b-003c5c6e12bc:88caee579f8eb13c7c5d147ba8ada29b9c7df548/wide-1600-900/Color%20Line%20Stadion.jpg",
				"owner": "",
				"width": 0,
				"height": 0,
				"size": 0
			},
			{
				"name": "1174_002.jpg",
				"source": "https://www.aafk.no/historisk-arkiv/nyheter/vare-baner-color-line-stadion/_/image/8e00fdd2-5203-4a17-8440-ae6f9f484544:9bfcecefdff424100378306f385ee5af4c0cc41a/wide-1600-900/_DSC8371_HDR.jpg",
				"owner": "",
				"width": 0,
				"height": 0,
				"size": 0
			},
			{
				"name": "1174_003.jpg",
				"source": "https://upload.wikimedia.org/wikipedia/commons/thumb/b/be/Color_Line_stadion.jpg/1200px-Color_Line_stadion.jpg",
				"owner": "",
				"width": 0,
				"height": 0,
				"size": 0
			},
			{
				"name": "1174_004.jpg",
				"source": "https://football-stadiums.ru/wp-content/uploads/2023/11/color-line-stadion-13.jpg",
				"owner": "",
				"width": 0,
				"height": 0,
				"size": 0
			}
		],
		"no": 22
	},
	{
		"team": {
			"api_football_id": 758,
			"name": "Sogndal",
			"code": "SOG",
			"country": "Norway",
			"founded": 1926,
			"wiki": "https://en.wikipedia.org/wiki/Sogndal_Fotball"
		},
		"venue": {
			"api_football_id": 1195,
			"name": "Fosshaugane Campus",
			"address": "Trolladalen 26",
			"city": "Sogndal",
			"capacity": 5623,
			"surface": "artificial turf",
			"lat": 61.231722,
			"lng": 7.08575,
			"x": 158,
			"y": 796,
			"wiki": "https://en.wikipedia.org/wiki/Fosshaugane_Campus"
		},
		"league": {},
		"images": [
			{
				"name": "1195_001.jpg",
				"source": "https://www.sogndalfotball.no/fosshaugane/_/image/338034ad-e338-4240-bc1b-b5824b5fecb1:20580ed1c020d94d684b916f59280bfaa421c2c6/wide-1600-900/DJI_0750.jpg",
				"owner": "",
				"width": 0,
				"height": 0,
				"size": 0
			},
			{
				"name": "1195_002.jpg",
				"source": "https://www.sogndalfotball.no/nyheiter/informasjon-kring-renovering-av-svingenbygget-pa-fosshaugane-campus/_/image/04a82aa8-3c3c-422b-a036-f92a3278c913:e0cb28cbf12c0c65fbb6bc7b0434a5b47a27a13c/wide-1600-900/DJI_0853.jpg",
				"owner": "",
				"width": 0,
				"height": 0,
				"size": 0
			},
			{
				"name": "1195_003.jpg",
				"source": "https://upload.wikimedia.org/wikipedia/commons/e/e9/Sogndal_Stadion.JPG",
				"owner": "",
				"width": 0,
				"height": 0,
				"size": 0
			},
			{
				"name": "1195_004.jpg",
				"source": "https://www.sogndalfotball.no/fosshaugane/fosshaugane-campus/_/image/ae63bbf1-5f6e-4338-91e8-aed6f15b3dc3:bf0e1d197c3326c7547da6828e7d89ef84f4eafb/wide-1600-900/Falkeblikk%20AS%20-%20Dronebilde%20Fosshaugane%20Campus1600x1066.jpg",
				"owner": "",
				"width": 0,
				"height": 0,
				"size": 0
			}
		],
		"no": 23
	},
	{
		"team": {
			"api_football_id": 2144,
			"name": "Kongsvinger",
			"code": "ANA",
			"country": "Norway",
			"founded": 1892,
			"wiki": "https://en.wikipedia.org/wiki/Kongsvinger_IL_Toppfotball"
		},
		"venue": {
			"api_football_id": 1180,
			"name": "Gjemselund Stadion",
			"address": "Brugata 47 B",
			"city": "Kongsvinger",
			"capacity": 5684,
			"surface": "artificial turf",
			"lat": 60.195278,
			"lng": 11.987222,
			"x": 314,
			"y": 863,
			"wiki": "https://en.wikipedia.org/wiki/Gjemselund_Stadion"
		},
		"league": {},
		"images": [
			{
				"name": "1180_001.jpg",
				"source": "https://g.acdn.no/obscura/API/dynamic/r1/escenic/tr_2000_2000_s_f/0000/archive/04546/Gjemselund_4546834a.jpg?chk=E5F2AF",
				"owner": "",
				"width": 0,
				"height": 0,
				"size": 0
			},
			{
				"name": "1180_002.jpg",
				"source": "https://groundhopping.carlluis.de/storage/fotos/large/249/Gjemselund%20stadion-002-Haupttribuene.jpg",
				"owner": "",
				"width": 0,
				"height": 0,
				"size": 0
			},
			{
				"name": "1180_003.jpg",
				"source": "https://pbs.twimg.com/media/EgqsvW-WkAANWQQ.jpg:large",
				"owner": "",
				"width": 0,
				"height": 0,
				"size": 0
			}
		],
		"no": 24
	},
	{
		"team": {
			"api_football_id": 2148,
			"name": "Asane",
			"code": "ASA",
			"country": "Norway",
			"founded": 1971,
			"wiki": "https://en.wikipedia.org/wiki/%C3%85sane_Fotball"
		},
		"venue": {
			"api_football_id": 12683,
			"name": "Åsane Arena",
			"address": "Myrdalsvegen 155, Nyborg",
			"city": "Bergen",
			"capacity": 3507,
			"surface": "artificial turf",
			"lat": 60.469639,
			"lng": 5.314611,
			"x": 101,
			"y": 845,
			"wiki": "https://en.wikipedia.org/wiki/%C3%85sane_Arena"
		},
		"league": {},
		"images": [
			{
				"name": "12683_001.jpg",
				"source": "https://www.asanefotball.no/nyheter/na-blir-apningskampen-enda-goyere/_/image/dd4209a3-0da3-4a81-aa6c-1b123cbddfc5:099574e6a542ab5bce8ee50b2330f3dab11f8d20/wide-1600-900/%C3%85sane%20Arena%20hovedtribune%2017%20sept%202021.jpg",
				"owner": "",
				"width": 0,
				"height": 0,
				"size": 0
			},
			{
				"name": "12683_002.jpg",
				"source": "https://www.asanefotball.no/nyheter/venter-med-arena-oppstart-grunnet-granulat-mangel-i-europa/_/image/5b667ed6-fe4f-4f37-bb86-bc4190f7e79d:693e4bc3b2dba2f8d0d06f6a50e4f76ef88e65be/wide-1600-900/%C3%85sane%20Arena%201%20sept%202021.jpg",
				"owner": "",
				"width": 0,
				"height": 0,
				"size": 0
			},
			{
				"name": "12683_003.jpg",
				"source": "https://www.brann.no/nyheter/sondagens-cupkamp-spilles-pa-asane-arena-klokken-13.00/_/image/15ffe18d-7852-451e-b7a5-1cd78a4b5214:02dff3df77c63deb21b1b04c1df710443dfbc2a4/wide-1600-900/BB221002BB266.jpg",
				"owner": "",
				"width": 0,
				"height": 0,
				"size": 0
			},
			{
				"name": "12683_004.jpg",
				"source": "https://res.cloudinary.com/iml/image/upload/w_750,c_scale/c_crop,g_custom/w_1024,c_scale/v1676299419/widgetdocs/LA_Asane_Arena_4_ajvevg.jpg",
				"owner": "",
				"width": 0,
				"height": 0,
				"size": 0
			}
		],
		"no": 25
	},
	{
		"team": {
			"api_football_id": 2150,
			"name": "hodd",
			"code": "HOD",
			"country": "Norway",
			"founded": 1919,
			"wiki": "https://en.wikipedia.org/wiki/IL_H%C3%B8dd"
		},
		"venue": {
			"api_football_id": 2794,
			"name": "Nye Høddvoll Stadion",
			"address": "Høddvollveien 10",
			"city": "Ulsteinvik",
			"capacity": 4081,
			"surface": "artificial turf",
			"lat": 62.339694,
			"lng": 5.881472,
			"x": 119,
			"y": 721,
			"wiki": "https://en.wikipedia.org/wiki/Nye_H%C3%B8ddvoll"
		},
		"league": {},
		"images": [
			{
				"name": "2794_001.jpg",
				"source": "https://www.bucci.no/uploads/1/3/1/7/131704164/published/nye-ulsteinhallen-hovudtribune-front.jpg?1587557559",
				"owner": "",
				"width": 0,
				"height": 0,
				"size": 0
			},
			{
				"name": "2794_002.jpg",
				"source": "https://paabortebane.no/wp-content/uploads/2021/08/8.-H%C3%B8dd-RED-scaled.jpg",
				"owner": "",
				"width": 0,
				"height": 0,
				"size": 0
			},
			{
				"name": "2794_003.jpg",
				"source": "https://www.bucci.no/uploads/1/3/1/7/131704164/published/nye-ulsteinhallen-hovudtribune-fr-veg.jpg?1587557694",
				"owner": "",
				"width": 0,
				"height": 0,
				"size": 0
			},
			{
				"name": "2794_004.jpg",
				"source": "https://image.nernett.no/209396.jpg?imageId=209396&x=0&y=0&cropw=100&croph=100&panox=0&panoy=0&panow=100&panoh=100&width=1200&height=683",
				"owner": "",
				"width": 0,
				"height": 0,
				"size": 0
			}
		],
		"no": 26
	},
	{
		"team": {
			"api_football_id": 2152,
			"name": "Mjondalen",
			"code": "MJO",
			"country": "Norway",
			"founded": 1910,
			"wiki": "https://en.wikipedia.org/wiki/Mj%C3%B8ndalen_IF"
		},
		"venue": {
			"api_football_id": 1183,
			"name": "Consto Arena",
			"address": "Hagatjernsveien 17, Nedre Eiker",
			"city": "Mjøndalen",
			"capacity": 4350,
			"surface": "artificial turf",
			"lat": 59.746949,
			"lng": 10.014616,
			"x": 251,
			"y": 891,
			"wiki": "https://en.wikipedia.org/wiki/Consto_Arena"
		},
		"league": {},
		"images": [
			{
				"name": "1183_001.jpg",
				"source": "https://www.miffotball.no/om-stadion/_/image/c397477f-2a9d-4d9e-a2ea-71c9239f8d26:a55b5c53f9832b8be70d21b64abadbcf3544e424/wide-1600-900/stadion.jpg",
				"owner": "",
				"width": 0,
				"height": 0,
				"size": 0
			},
			{
				"name": "1183_002.jpg",
				"source": "https://upload.wikimedia.org/wikipedia/commons/e/ea/Mj%C3%B8ndalen_stadion_IMG_6949.jpg",
				"owner": "",
				"width": 0,
				"height": 0,
				"size": 0
			}
		],
		"no": 27
	},
	{
		"team": {
			"api_football_id": 2153,
			"name": "Raufoss",
			"code": "RAU",
			"country": "Norway",
			"founded": 1918,
			"wiki": "https://en.wikipedia.org/wiki/Raufoss_IL"
		},
		"venue": {
			"api_football_id": 1189,
			"name": "NAMMO stadion",
			"address": "Stadionløkka 4",
			"city": "Raufoss",
			"capacity": 3042,
			"surface": "artificial turf",
			"lat": 60.72103,
			"lng": 10.602567,
			"x": 270,
			"y": 829,
			"wiki": "https://en.wikipedia.org/wiki/Nammo_Stadion"
		},
		"league": {},
		"images": [
			{
				"name": "1189_001.jpg",
				"source": "https://www.raufossfotball.no/nyheter/en-hilsen-fra-a-laget-vi-sees-pa-nammo-stadion/_/image/5ff4b8fd-82e0-4435-a9e4-0fde073f6660:2ed3783e988e54b1746d1ae4c82340d62d64927c/wide-1600-900/kampdag_stadion%20kopi.jpg",
				"owner": "",
				"width": 0,
				"height": 0,
				"size": 0
			},
			{
				"name": "1189_002.jpg",
				"source": "https://www.raufossfotball.no/nyheter/arets-siste-kamp-pa-nammo-stadion/_/image/36f3b42a-25a9-4499-8fda-83b92109b5fe:5a6115f765bbb495effea4e9016891987f5fe52a/wide-1600-900/nammo%20desember.jpg",
				"owner": "",
				"width": 0,
				"height": 0,
				"size": 0
			}
		],
		"no": 28
	},
	{
		"team": {
			"api_football_id": 2239,
			"name": "Skeid",
			"code": "SKE",
			"country": "Norway",
			"founded": 1915,
			"wiki": "https://en.wikipedia.org/wiki/Skeid_Fotball"
		},
		"venue": {
			"api_football_id": 1194,
			"name": "Nordre Åsen kunstgress",
			"address": "Kjelsåsveien 9",
			"city": "Oslo",
			"capacity": 2623,
			"surface": "artificial turf",
			"lat": 59.942664,
			"lng": 10.786234,
			"x": 276,
			"y": 879,
			"wiki": ""
		},
		"league": {},
		"images": [
			{
				"name": "1194_001.jpg",
				"source": "https://www.skeid.no/nyheter/skeidbanen-ti-ar-som-vart-hjem/_/image/1f33f608-501c-4f61-a037-390c77f30b80:aeb063b3442531a707da8d7b50c74dba449f95b6/wide-1600-900/DJI_0175.jpg",
				"owner": "",
				"width": 0,
				"height": 0,
				"size": 0
			},
			{
				"name": "1194_002.jpg",
				"source": "https://paabortebane.no/wp-content/uploads/2017/05/Nordre-%C3%85sen.jpg",
				"owner": "",
				"width": 0,
				"height": 0,
				"size": 0
			}
		],
		"no": 29
	},
	{
		"team": {
			"api_football_id": 6976,
			"name": "Egersund",
			"code": "EGE",
			"country": "Norway",
			"founded": 1919,
			"wiki": "https://en.wikipedia.org/wiki/Egersunds_IK"
		},
		"venue": {
			"api_football_id": 5094,
			"name": "Egersund Idrettsparken",
			"address": "Kjeld Bugges gate",
			"city": "Egersund",
			"capacity": 1924,
			"surface": "grass",
			"lat": 58.446022,
			"lng": 5.999575,
			"x": 123,
			"y": 972,
			"wiki": ""
		},
		"league": {},
		"images": [
			{
				"name": "5094_001.jpg",
				"source": "https://premium.vgc.no/v2/images/3e150e69-90b1-47e4-8aee-8cb1c7dfb601?fit=crop&format=auto&h=1069&w=1900&s=880b12ae8cfcd0bcb0833cb55d0274d05751ae95",
				"owner": "",
				"width": 0,
				"height": 0,
				"size": 0
			},
			{
				"name": "5094_002.jpg",
				"source": "https://g.acdn.no/obscura/API/dynamic/r1/ece5/tr_2000_2000_s_f/0000/dala/2021/10/6/13/IMG_5607.JPG?chk=D5560A",
				"owner": "",
				"width": 0,
				"height": 0,
				"size": 0
			}
		],
		"no": 30
	},
	{
		"team": {
			"api_football_id": 7006,
			"name": "Lyn",
			"code": "LYN",
			"country": "Norway",
			"founded": 1896,
			"wiki": "https://en.wikipedia.org/wiki/Lyn_Fotball"
		},
		"venue": {
			"api_football_id": 19421,
			"name": "Bislett Stadion",
			"address": "Dalsbergstien 17, St. Hanshaugen",
			"city": "Oslo",
			"capacity": 15400,
			"surface": "grass",
			"lat": 59.924722,
			"lng": 10.733333,
			"x": 274,
			"y": 880,
			"wiki": "https://en.wikipedia.org/wiki/Bislett_Stadium"
		},
		"league": {},
		"images": [
			{
				"name": "19421_001.jpg",
				"source": "https://img.olympics.com/images/image/private/t_s_pog_staticContent_hero_xl_2x/f_auto/primary/gvzornzhpdnexznb5lsi",
				"owner": "",
				"width": 0,
				"height": 0,
				"size": 0
			},
			{
				"name": "19421_002.jpg",
				"source": "https://live.staticflickr.com/4276/34393308524_a1836b968a_h.jpg",
				"owner": "",
				"width": 0,
				"height": 0,
				"size": 0
			},
			{
				"name": "19421_003.jpg",
				"source": "https://dynamic-media-cdn.tripadvisor.com/media/photo-o/19/ed/92/55/img-20191102-105913-largejpg.jpg?w=1200&h=-1&s=1",
				"owner": "",
				"width": 0,
				"height": 0,
				"size": 0
			},
			{
				"name": "19421_004.jpg",
				"source": "https://i.ytimg.com/vi/XtP0oBizbvE/maxresdefault.jpg",
				"owner": "",
				"width": 0,
				"height": 0,
				"size": 0
			}
		],
		"no": 31
	},
	{
		"team": {
			"api_football_id": 7012,
			"name": "Moss",
			"code": "MOS",
			"country": "Norway",
			"founded": 1906,
			"wiki": "https://en.wikipedia.org/wiki/Moss_FK"
		},
		"venue": {
			"api_football_id": 5124,
			"name": "Melløs Stadion",
			"address": "Kallumvegen 6A, Melløs",
			"city": "Moss",
			"capacity": 9410,
			"surface": "grass",
			"lat": 59.420833,
			"lng": 10.671389,
			"x": 272,
			"y": 912,
			"wiki": "https://en.wikipedia.org/wiki/Mell%C3%B8s_Stadion"
		},
		"league": {},
		"images": [
			{
				"name": "5124_001.jpg",
				"source": "https://www.dagsavisen.no/resizer/p2zO3UhmEYMKAB5ABml4oH_4vmk=/arc-photo-mentormedier/eu-central-1-prod/public/J7ELTQT5TBHGFJMKHVWINGRMYA.jpg",
				"owner": "",
				"width": 0,
				"height": 0,
				"size": 0
			},
			{
				"name": "5124_002.jpg",
				"source": "https://www.mossfk.no/nyheter/velkommen-til-arsmote-i-moss-fk/_/image/2cbf8063-d4d2-49fe-9e40-378446f2a7e5:ccebfc3076e6371295d7f50777a3bce30175860a/wide-1600-900/Mell%C3%B8s%204.jpg",
				"owner": "",
				"width": 0,
				"height": 0,
				"size": 0
			},
			{
				"name": "5124_003.jpg",
				"source": "https://www.mossfk.no/mellos-stadion/stadion-og-reaksjonsreglement/_/image/44f2700c-a87b-4404-9d82-e13a655fd7c7:743e22a359b583fab910c13cf05313f6d475c4d9/wide-1600-900/66118228_2902942193054802_2454558901832515584_n.jpg",
				"owner": "",
				"width": 0,
				"height": 0,
				"size": 0
			},
			{
				"name": "5124_004.jpg",
				"source": "https://gfx.nrk.no/jqbhrsAlZkOFKGhVcHPe4gHr35KoVs6pjy7LrLZOftVw.jpg",
				"owner": "",
				"width": 0,
				"height": 0,
				"size": 0
			}
		],
		"no": 32
	},
	{
		"team": {
			"api_football_id": 2145,
			"name": "Levanger",
			"code": "LEV",
			"country": "Norway",
			"founded": 1996,
			"wiki": "https://en.wikipedia.org/wiki/Levanger_FK"
		},
		"venue": {
			"api_football_id": 1952,
			"name": "TOBB ARENA Levanger",
			"address": "Saltkjelen 3",
			"city": "Levanger",
			"capacity": 6000,
			"surface": "artificial turf",
			"lat": 63.741217,
			"lng": 11.278237,
			"x": 291,
			"y": 623,
			"wiki": ""
		},
		"league": {},
		"images": [
			{
				"name": "1952_001.jpg",
				"source": "https://www.levangerfk.no/om-stadion/_/image/6e0c7aa0-35b4-4ecb-98a1-c22d00a1ead6:ab662916ec61516b6dab4722ee04efcd522496f2/wide-1600-900/Tobb%20Arena1.jpg",
				"owner": "",
				"width": 0,
				"height": 0,
				"size": 0
			},
			{
				"name": "1952_002.jpg",
				"source": "https://sortitoutsidospaces.b-cdn.net/media/YvpwdIetzHQxj9q8GSxVQwQF3sLpNdIZo8Xh70YC.jpg",
				"owner": "",
				"width": 0,
				"height": 0,
				"size": 0
			}
		],
		"no": 33
	},
	{
		"team": {
			"api_football_id": 2146,
			"name": "Sandnes ULF",
			"code": "SAN",
			"country": "Norway",
			"founded": 1911,
			"wiki": "https://en.wikipedia.org/wiki/Sandnes_Ulf"
		},
		"venue": {
			"api_football_id": 12682,
			"name": "Øster Hus Arena",
			"address": "Jønningsheiveien 40",
			"city": "Sandnes",
			"capacity": 6046,
			"surface": "artificial turf",
			"lat": 58.861369,
			"lng": 5.720963,
			"x": 114,
			"y": 946,
			"wiki": "https://en.wikipedia.org/wiki/%C3%98ster_Hus_Arena"
		},
		"league": {},
		"images": [
			{
				"name": "12682_001.jpg",
				"source": "https://holon.no/wp-content/uploads/2021/10/Osterhus-arena-panorama-bak-ma%CC%8Al.jpeg",
				"owner": "",
				"width": 0,
				"height": 0,
				"size": 0
			},
			{
				"name": "12682_002.jpg",
				"source": "https://holon.no/wp-content/uploads/2021/10/Osterhus-arena-MAX_0350-e1635511369204.jpeg",
				"owner": "",
				"width": 0,
				"height": 0,
				"size": 0
			},
			{
				"name": "12682_003.jpg",
				"source": "https://premium.vgc.no/v2/images/7c13bd86-38df-4567-86ba-e4bbe1df3229?fit=crop&format=auto&h=1011&w=1900&s=8b6b6c50ccca63b549b4182768ffe41894cae057",
				"owner": "",
				"width": 0,
				"height": 0,
				"size": 0
			},
			{
				"name": "12682_004.jpg",
				"source": "https://www.sandnesulf.no/nyheter/konferanser-og-arrangement-pa-oster-hus-arena/_/image/0ff9b584-e1f3-44a8-b5f4-ea98cb2e01a4:747522547931adb9b56bb15dce87cfc1555cb3ba/wide-1600-900/Konferansesenter.jpg",
				"owner": "",
				"width": 0,
				"height": 0,
				"size": 0
			},
			{
				"name": "12682_005.jpg",
				"source": "https://www.randi.dk/wp-content/uploads/2022/09/Nanco-Hoogstad-0662-2-topaz-scaled.jpg",
				"owner": "",
				"width": 0,
				"height": 0,
				"size": 0
			}
		],
		"no": 34
	},
	{
		"team": {
			"api_football_id": 2151,
			"name": "jerv",
			"code": "JER",
			"country": "Norway",
			"founded": 1921,
			"wiki": "https://en.wikipedia.org/wiki/FK_Jerv"
		},
		"venue": {
			"api_football_id": 1751,
			"name": "J.J. Ugland Stadion",
			"address": "Levermyrveien 30",
			"city": "Grimstad",
			"capacity": 3766,
			"surface": "grass",
			"lat": 58.3455,
			"lng": 8.59172,
			"x": 206,
			"y": 978,
			"wiki": "https://en.wikipedia.org/wiki/J.J._Ugland_Stadion_%E2%80%93_Levermyr"
		},
		"league": {},
		"images": [
			{
				"name": "1751_001.jpg",
				"source": "https://www.fkjerv.no/om-klubben/levermyr-stadion/_/image/3205e697-724a-4666-9564-75e56328db43:4048c6f649da8244a8cab03495e3a0157b2f47f9/wide-1600-900/CAF1F92C-AF34-496A-9C03-BA73226252%2013%20(3).jpg",
				"owner": "",
				"width": 0,
				"height": 0,
				"size": 0
			},
			{
				"name": "1751_002.jpg",
				"source": "https://pbs.twimg.com/media/Dj2HXUgX4AIYz-P?format=jpg&name=large",
				"owner": "",
				"width": 0,
				"height": 0,
				"size": 0
			}
		],
		"no": 35
	}
]